grpc_router/__init__.py
grpc_router/server.py
grpc_router-0.3.0.dist-info/AUTHORS.md
grpc_router-0.3.0.dist-info/LICENSE
grpc_router-0.3.0.dist-info/METADATA
grpc_router-0.3.0.dist-info/WHEEL
grpc_router-0.3.0.dist-info/top_level.txt
grpc_router-0.3.0.dist-info/RECORD
