Metadata-Version: 2.1
Name: grpc_router
Version: 0.3.0
Summary: A simple grpc router to establish a simple grpc mesh.
Author-email: Ciprian Miclaus <ciprianm@gmail.com>
License: MIT License
Project-URL: homepage, https://github.com/ciprianmiclaus2/grpc_router
Project-URL: documentation, https://ciprianmiclaus2.github.io/grpc_router/
Project-URL: repository, https://github.com/ciprianmiclaus2/grpc_router
Project-URL: history, https://github.com/ciprianmiclaus2/grpc_router/blob/main/HISTORY.md
Classifier: Development Status :: 4 - Beta
Classifier: Intended Audience :: Developers
Classifier: License :: OSI Approved :: MIT License
Classifier: Natural Language :: English
Classifier: Programming Language :: Python :: 3
Classifier: Programming Language :: Python :: 3.9
Classifier: Programming Language :: Python :: 3.10
Classifier: Programming Language :: Python :: 3.11
Classifier: Programming Language :: Python :: 3.12
Classifier: Programming Language :: Python :: 3.13
Requires-Python: >=3.9
License-File: LICENSE
License-File: AUTHORS.md
Requires-Dist: grpcio
Requires-Dist: grpcio-reflection
Requires-Dist: grpcio-health-checking
Requires-Dist: protobuf
Provides-Extra: dev
Requires-Dist: grpcio-tools ; extra == 'dev'
Requires-Dist: tox ; extra == 'dev'
Requires-Dist: pre-commit ; extra == 'dev'
Requires-Dist: pip ; extra == 'dev'
Requires-Dist: twine ; extra == 'dev'
Requires-Dist: toml ; extra == 'dev'
Provides-Extra: test
Requires-Dist: pytest ; extra == 'test'
